Workbook

Sheet Products
A1: AL-NOOR TRADING COMPANY — PRODUCT MASTER CATALOG (Lahore, Pakistan)
A2: Product ID | B2: Category | C2: Sub-Category | D2: Product Name | E2: SKU | F2: Unit | G2: Reorder Level | H2: Reorder Qty | I2: Cost Price (PKR) | J2: Sale Price (PKR) | K2: Gross Margin (PKR) | L2: Margin % | M2: Supplier | N2: Brand | O2: Status
A3: PK-1001 | B3: Electronics & Appliances | C3: Mobile Phones | D3: Samsung Galaxy A54 | E3: SMA54 | F3: Unit | G3: 1 | H3: 10 | I3: 75000 | J3: 95000 | K3: =J3-I3 -> 20000 | L3: =IF(J3>0,(J3-I3)/J3,0) -> 0.21052632 | M3: TechHub Pvt Ltd | N3: Samsung | O3: Active
A4: PK-1002 | B4: Electronics & Appliances | C4: Mobile Phones | D4: Samsung Galaxy A34 | E4: SMA34 | F4: Unit | G4: 2 | H4: 10 | I4: 55000 | J4: 68000 | K4: =J4-I4 -> 13000 | L4: =IF(J4>0,(J4-I4)/J4,0) -> 0.19117647 | M4: TechHub Pvt Ltd | N4: Samsung | O4: Active
A5: PK-1003 | B5: Electronics & Appliances | C5: Mobile Phones | D5: iPhone 14 | E5: IPH14 | F5: Unit | G5: 1 | H5: 5 | I5: 240000 | J5: 279000 | K5: =J5-I5 -> 39000 | L5: =IF(J5>0,(J5-I5)/J5,0) -> 0.13978495 | M5: iWorld Pakistan | N5: Apple | O5: Active
A6: PK-1004 | B6: Electronics & Appliances | C6: Mobile Phones | D6: iPhone 13 | E6: IPH13 | F6: Unit | G6: 1 | H6: 5 | I6: 185000 | J6: 215000 | K6: =J6-I6 -> 30000 | L6: =IF(J6>0,(J6-I6)/J6,0) -> 0.13953488 | M6: iWorld Pakistan | N6: Apple | O6: Active
A7: PK-1005 | B7: Electronics & Appliances | C7: Mobile Phones | D7: Vivo Y36 | E7: VIVY36 | F7: Unit | G7: 3 | H7: 15 | I7: 42000 | J7: 52000 | K7: =J7-I7 -> 10000 | L7: =IF(J7>0,(J7-I7)/J7,0) -> 0.19230769 | M7: Vivo Pakistan | N7: Vivo | O7: Active
A8: PK-1006 | B8: Electronics & Appliances | C8: Mobile Phones | D8: Vivo V27 | E8: VIVV27 | F8: Unit | G8: 2 | H8: 10 | I8: 65000 | J8: 80000 | K8: =J8-I8 -> 15000 | L8: =IF(J8>0,(J8-I8)/J8,0) -> 0.1875 | M8: Vivo Pakistan | N8: Vivo | O8: Active
A9: PK-1007 | B9: Electronics & Appliances | C9: Mobile Phones | D9: Oppo A78 | E9: OPPA78 | F9: Unit | G9: 3 | H9: 15 | I9: 38000 | J9: 47000 | K9: =J9-I9 -> 9000 | L9: =IF(J9>0,(J9-I9)/J9,0) -> 0.19148936 | M9: Oppo Distributors | N9: Oppo | O9: Active
A10: PK-1008 | B10: Electronics & Appliances | C10: Mobile Phones | D10: Oppo Reno10 | E10: OPPR10 | F10: Unit | G10: 1 | H10: 8 | I10: 82000 | J10: 99000 | K10: =J10-I10 -> 17000 | L10: =IF(J10>0,(J10-I10)/J10,0) -> 0.17171717 | M10: Oppo Distributors | N10: Oppo | O10: Active
A11: PK-1009 | B11: Electronics & Appliances | C11: Mobile Phones | D11: Realme 11 Pro | E11: RLM11P | F11: Unit | G11: 3 | H11: 15 | I11: 52000 | J11: 65000 | K11: =J11-I11 -> 13000 | L11: =IF(J11>0,(J11-I11)/J11,0) -> 0.2 | M11: Realme Pakistan | N11: Realme | O11: Active
A12: PK-1010 | B12: Electronics & Appliances | C12: Mobile Phones | D12: Xiaomi Redmi 12 | E12: XMR12 | F12: Unit | G12: 4 | H12: 20 | I12: 34000 | J12: 42000 | K12: =J12-I12 -> 8000 | L12: =IF(J12>0,(J12-I12)/J12,0) -> 0.19047619 | M12: Xiaomi Pakistan | N12: Xiaomi | O12: Active
A13: PK-1011 | B13: Electronics & Appliances | C13: Laptops & Computers | D13: Dell Inspiron 15 | E13: DELI15 | F13: Unit | G13: 1 | H13: 5 | I13: 115000 | J13: 139000 | K13: =J13-I13 -> 24000 | L13: =IF(J13>0,(J13-I13)/J13,0) -> 0.17266187 | M13: Dell Pakistan | N13: Dell | O13: Active
A14: PK-1012 | B14: Electronics & Appliances | C14: Laptops & Computers | D14: HP Pavilion 14 | E14: HPP14 | F14: Unit | G14: 1 | H14: 5 | I14: 108000 | J14: 130000 | K14: =J14-I14 -> 22000 | L14: =IF(J14>0,(J14-I14)/J14,0) -> 0.16923077 | M14: HP Distributors | N14: HP | O14: Active
... A216: PK-1214 | B216: Automobiles & Accessories | C216: Car Accessories | D216: Dashcam 1080p | E216: DSHCM | F216: Unit | G216: 3 | H216: 10 | I216: 5500 | J216: 8000 | K216: =J216-I216 -> 2500 | L216: =IF(J216>0,(J216-I216)/J216,0) -> 0.3125 | M216: Xiaomi Pakistan | N216: Xiaomi | O216: Active

Sheet Sheet1
A1: Product ID | B1: Category | C1: Product Name | D1: Qty in Hand | E1: Cost Price (PKR) | F1: Sale Price (PKR) | G1: 46023 | H1: 46024 | I1: 46025 | J1: 46026 | K1: 46027 | L1: 46028 | M1: 46029 | N1: 46030 | O1: 46031 | P1: 46032 | Q1: 46033 | R1: 46034 | S1: 46035 | T1: 46036 | U1: 46037 | V1: 46038 | W1: 46039 | X1: 46040 | Y1: 46041 | Z1: 46042 | AA1: 46043 | AB1: 46044 | AC1: 46045 | AD1: 46046 | AE1: 46047 | AF1: 46048 | AG1: 46049 | AH1: 46050 | AI1: 46051 | AJ1: 46052
A2: PK-1001 | B2: Electronics & Appliances | C2: Samsung Galaxy A54 | D2: 138 | E2: 75000 | F2: 95000
A3: PK-1002 | B3: Electronics & Appliances | C3: Samsung Galaxy A34 | D3: 74 | E3: 55000 | F3: 68000
A4: PK-1003 | B4: Electronics & Appliances | C4: iPhone 14 | D4: 7 | E4: 240000 | F4: 279000
A5: PK-1004 | B5: Electronics & Appliances | C5: iPhone 13 | D5: 53 | E5: 185000 | F5: 215000
A6: PK-1005 | B6: Electronics & Appliances | C6: Vivo Y36 | D6: 65 | E6: 42000 | F6: 52000
A7: PK-1006 | B7: Electronics & Appliances | C7: Vivo V27 | D7: 12 | E7: 65000 | F7: 80000
A8: PK-1007 | B8: Electronics & Appliances | C8: Oppo A78 | D8: 101 | E8: 38000 | F8: 47000
A9: PK-1008 | B9: Electronics & Appliances | C9: Oppo Reno10 | D9: 96 | E9: 82000 | F9: 99000
A10: PK-1009 | B10: Electronics & Appliances | C10: Realme 11 Pro | D10: 34 | E10: 52000 | F10: 65000
A11: PK-1010 | B11: Electronics & Appliances | C11: Xiaomi Redmi 12 | D11: 20 | E11: 34000 | F11: 42000
A12: PK-1011 | B12: Electronics & Appliances | C12: Dell Inspiron 15 | D12: 118 | E12: 115000 | F12: 139000
A13: PK-1012 | B13: Electronics & Appliances | C13: HP Pavilion 14 | D13: 1 | E13: 108000 | F13: 130000
... A215: PK-1214 | B215: Automobiles & Accessories | C215: Dashcam 1080p | D215: 29 | E215: 5500 | F215: 8000

Sheet Purchase Orders
A1: PURCHASE ORDERS — AL-NOOR TRADING COMPANY (Jan–Dec 2024)
A2: PO Number | B2: Date | C2: Supplier ID | D2: Supplier Name | E2: Product ID | F2: Product Name | G2: Category | H2: Qty Ordered | I2: Unit Cost (PKR) | J2: Total Cost (PKR) | K2: Status | L2: Payment Status
A3: PO-2024001 | B3: 2024-10-19 | C3: SUP-013 | D3: Haier Pakistan | E3: RLM11P | F3: Realme 11 Pro | G3: Electronics & Appliances | H3: 66 | I3: 52000 | J3: =H3*I3 -> 3432000 | K3: Received | L3: Paid
A4: PO-2024002 | B4: 2024-08-24 | C4: SUP-055 | D4: Shell Pakistan | E4: CSCSFT | F4: Car Seat Cover Full Set | G4: Automobiles & Accessories | H4: 40 | I4: 2500 | J4: =H4*I4 -> 100000 | K4: Partially Received | L4: Paid
A5: PO-2024003 | B5: 2024-09-23 | C5: SUP-046 | D5: Amreli Steels | E5: CPVCP12 | F5: CPVC Pipe 1/2 inch | G5: Construction & Hardware | H5: 14 | I5: 180 | J5: =H5*I5 -> 2520 | K5: Partially Received | L5: Unpaid
A6: PO-2024004 | B6: 2024-07-03 | C6: SUP-013 | D6: Haier Pakistan | E6: HPP14 | F6: HP Pavilion 14 | G6: Electronics & Appliances | H6: 22 | I6: 108000 | J6: =H6*I6 -> 2376000 | K6: Pending | L6: Partially Paid
A7: PO-2024005 | B7: 2024-08-03 | C7: SUP-022 | D7: Shan Foods | E7: KNCST400 | F7: K&N's Chicken Strips 400g | G7: Grocery & Food Items | H7: 38 | I7: 750 | J7: =H7*I7 -> 28500 | K7: Cancelled | L7: Paid
A8: PO-2024006 | B8: 2024-12-17 | C8: SUP-037 | D8: Sana Safinaz | E8: JMSHRT | F8: J. Men Shirt | G8: Clothing & Textiles | H8: 51 | I8: 1800 | J8: =H8*I8 -> 91800 | K8: Partially Received | L8: Partially Paid
A9: PO-2024007 | B9: 2024-05-02 | C9: SUP-047 | D9: Pakistan Cables | E9: MLCEM | F9: Maple Leaf Cement 50kg | G9: Construction & Hardware | H9: 53 | I9: 845 | J9: =H9*I9 -> 44785 | K9: Received | L9: Unpaid
A10: PO-2024008 | B10: 2024-01-03 | C10: SUP-019 | D10: Falak Foods | E10: RFAHZA | F10: Rooh Afza 800ml | G10: Grocery & Food Items | H10: 29 | I10: 480 | J10: =H10*I10 -> 13920 | K10: Pending | L10: Unpaid
A11: PO-2024009 | B11: 2024-07-06 | C11: SUP-054 | D11: Castrol Pakistan | E11: NGKSP4 | F11: NGK Spark Plug Set 4 | G11: Automobiles & Accessories | H11: 45 | I11: 1200 | J11: =H11*I11 -> 54000 | K11: Cancelled | L11: Partially Paid
A12: PO-2024010 | B12: 2024-08-28 | C12: SUP-014 | D12: Dawlance | E12: MBAIM2 | F12: Apple MacBook Air M2 | G12: Electronics & Appliances | H12: 79 | I12: 290000 | J12: =H12*I12 -> 22910000 | K12: Pending | L12: Unpaid
A13: PO-2024011 | B13: 2024-03-21 | C13: SUP-021 | D13: National Foods | E13: TAPDN500 | F13: Tapal Danedar 500g | G13: Grocery & Food Items | H13: 35 | I13: 580 | J13: =H13*I13 -> 20300 | K13: Received | L13: Paid
A14: PO-2024012 | B14: 2024-09-11 | C14: SUP-037 | D14: Sana Safinaz | E14: JMSHRT | F14: J. Men Shirt | G14: Clothing & Textiles | H14: 89 | I14: 1800 | J14: =H14*I14 -> 160200 | K14: Received | L14: Unpaid
... A202: PO-2024200 | B202: 2024-01-29 | C202: SUP-046 | D202: Amreli Steels | E202: WLPTY20 | F202: Wall Putty 20kg | G202: Construction & Hardware | H202: 10 | I202: 1200 | J202: =H202*I202 -> 12000 | K202: Pending | L202: Paid

Sheet Sales History
A1: Product ID | B1: Category | C1: Product Name | D1: Qty in Hand | E1: Cost Price (PKR) | F1: Sale Price (PKR) | G1: 46023 | H1: 46024 | I1: 46025 | J1: 46026 | K1: 46027 | L1: 46028 | M1: 46029 | N1: 46030 | O1: 46031 | P1: 46032 | Q1: 46033 | R1: 46034 | S1: 46035 | T1: 46036 | U1: 46037 | V1: 46038 | W1: 46039 | X1: 46040 | Y1: 46041 | Z1: 46042 | AA1: 46043 | AB1: 46044 | AC1: 46045 | AD1: 46046 | AE1: 46047 | AF1: 46048 | AG1: 46049 | AH1: 46050 | AI1: 46051 | AJ1: 46052
A2: PK-1001 | B2: Electronics & Appliances | C2: Samsung Galaxy A54 | D2: 138 | E2: 75000 | F2: 95000 | K2: =MIN( IF(F2="Electronics & Appliances", IF(K2>0, IF(RANDBETWEEN(1,100)<=15,RANDBETWEEN(1,1),0), IF(RANDBETWEEN(1,100)<=35,RANDBETWEEN(1,2),0) ), IF(F2="Grocery & Food Items",RANDBETWEEN(5,20), IF(F2="Pharmaceuticals & Health",RANDBETWEEN(2,10), IF(F2="Clothing & Textiles",RANDBETWEEN(1,5), IF(F2="Construction & Hardware", IF(RANDBETWEEN(1,100)<=45,RANDBETWEEN(1,8),0), IF(F2="Stationery & Office Supplies",RANDBETWEEN(1,12), IF(F2="Automobiles & Accessories", IF(RANDBETWEEN(1,100)<=40,RANDBETWEEN(1,4),0), RANDBETWEEN(1,3)))))))), $D2-SUM($G2:K2)) -> 0 | L2: {=G2:H2} -> #VALUE! | M2: =MIN( IF(H2="Electronics & Appliances", IF(M2>0, IF(RANDBETWEEN(1,100)<=15,RANDBETWEEN(1,1),0), IF(RANDBETWEEN(1,100)<=35,RANDBETWEEN(1,2),0) ), IF(H2="Grocery & Food Items",RANDBETWEEN(5,20), IF(H2="Pharmaceuticals & Health",RANDBETWEEN(2,10), IF(H2="Clothing & Textiles",RANDBETWEEN(1,5), IF(H2="Construction & Hardware", IF(RANDBETWEEN(1,100)<=45,RANDBETWEEN(1,8),0), IF(H2="Stationery & Office Supplies",RANDBETWEEN(1,12), IF(H2="Automobiles & Accessories", IF(RANDBETWEEN(1,100)<=40,RANDBETWEEN(1,4),0), RANDBETWEEN(1,3)))))))), $D2-SUM($G2:M2)) -> #VALUE! | N2: =MIN( IF(I2="Electronics & Appliances", IF(N2>0, IF(RANDBETWEEN(1,100)<=15,RANDBETWEEN(1,1),0), IF(RANDBETWEEN(1,100)<=35,RANDBETWEEN(1,2),0) ), IF(I2="Grocery & Food Items",RANDBETWEEN(5,20), IF(I2="Pharmaceuticals & Health",RANDBETWEEN(2,10), IF(I2="Clothing & Textiles",RANDBETWEEN(1,5), IF(I2="Construction & Hardware", IF(RANDBETWEEN(1,100)<=45,RANDBETWEEN(1,8),0), IF(I2="Stationery & Office Supplies",RANDBETWEEN(1,12), IF(I2="Automobiles & Accessories", IF(RANDBETWEEN(1,100)<=40,RANDBETWEEN(1,4),0), RANDBETWEEN(1,3)))))))), $D2-SUM($G2:N2)) -> #VALUE! | O2: =MIN( IF(J2="Electronics & Appliances", IF(O2>0, IF(RANDBETWEEN(1,100)<=15,RANDBETWEEN(1,1),0), IF(RANDBETWEEN(1,100)<=35,RANDBETWEEN(1,2),0) ), IF(J2="Grocery & Food Items",RANDBETWEEN(5,20), IF(J2="Pharmaceuticals & Health",RANDBETWEEN(2,10), IF(J2="Clothing & Textiles",RANDBETWEEN(1,5), IF(J2="Construction & Hardware", IF(RANDBETWEEN(1,100)<=45,RANDBETWEEN(1,8),0), IF(J2="Stationery & Office Supplies",RANDBETWEEN(1,12), IF(J2="Automobiles & Accessories", IF(RANDBETWEEN(1,100)<=40,RANDBETWEEN(1,4),0), RANDBETWEEN(1,3)))))))), $D2-SUM($G2:O2)) -> #VALUE! | P2: =MIN( IF(K2="Electronics & Appliances", IF(P2>0, IF(RANDBETWEEN(1,100)<=15,RANDBETWEEN(1,1),0), IF(RANDBETWEEN(1,100)<=35,RANDBETWEEN(1,2),0) ), IF(K2="Grocery & Food Items",RANDBETWEEN(5,20), IF(K2="Pharmaceuticals & Health",RANDBETWEEN(2,10), IF(K2="Clothing & Textiles",RANDBETWEEN(1,5), IF(K2="Construction & Hardware", IF(RANDBETWEEN(1,100)<=45,RANDBETWEEN(1,8),0), IF(K2="Stationery & Office Supplies",RANDBETWEEN(1,12), IF(K2="Automobiles & Accessories", IF(RANDBETWEEN(1,100)<=40,RANDBETWEEN(1,4),0), RANDBETWEEN(1,3)))))))), $D2-SUM($G2:P2)) -> #VALUE! | Q2: =MIN( IF(L2="Electronics & Appliances", IF(Q2>0, IF(RANDBETWEEN(1,100)<=15,RANDBETWEEN(1,1),0), IF(RANDBETWEEN(1,100)<=35,RANDBETWEEN(1,2),0) ), IF(L2="Grocery & Food Items",RANDBETWEEN(5,20), IF(L2="Pharmaceuticals & Health",RANDBETWEEN(2,10), IF(L2="Clothing & Textiles",RANDBETWEEN(1,5), IF(L2="Construction & Hardware", IF(RANDBETWEEN(1,100)<=45,RANDBETWEEN(1,8),0), IF(L2="Stationery & Office Supplies",RANDBETWEEN(1,12), IF(L2="Automobiles & Accessories", IF(RANDBETWEEN(1,100)<=40,RANDBETWEEN(1,4),0), RANDBETWEEN(1,3)))))))), $D2-SUM($G2:Q2)) -> #VALUE! | R2: =MIN( IF(M2="Electronics & Appliances", IF(R2>0, IF(RANDBETWEEN(1,100)<=15,RANDBETWEEN(1,1),0), IF(RANDBETWEEN(1,100)<=35,RANDBETWEEN(1,2),0) ), IF(M2="Grocery & Food Items",RANDBETWEEN(5,20), IF(M2="Pharmaceuticals & Health",RANDBETWEEN(2,10), IF(M2="Clothing & Textiles",RANDBETWEEN(1,5), IF(M2="Construction & Hardware", IF(RANDBETWEEN(1,100)<=45,RANDBETWEEN(1,8),0), IF(M2="Stationery & Office Supplies",RANDBETWEEN(1,12), IF(M2="Automobiles & Accessories", IF(RANDBETWEEN(1,100)<=40,RANDBETWEEN(1,4),0), RANDBETWEEN(1,3)))))))), $D2-SUM($G2:R2)) -> #VALUE!
A3: PK-1002 | B3: Electronics & Appliances | C3: Samsung Galaxy A34 | D3: 74 | E3: 55000 | F3: 68000
A4: PK-1003 | B4: Electronics & Appliances | C4: iPhone 14 | D4: 7 | E4: 240000 | F4: 279000
A5: PK-1004 | B5: Electronics & Appliances | C5: iPhone 13 | D5: 53 | E5: 185000 | F5: 215000
A6: PK-1005 | B6: Electronics & Appliances | C6: Vivo Y36 | D6: 65 | E6: 42000 | F6: 52000
A7: PK-1006 | B7: Electronics & Appliances | C7: Vivo V27 | D7: 12 | E7: 65000 | F7: 80000
A8: PK-1007 | B8: Electronics & Appliances | C8: Oppo A78 | D8: 101 | E8: 38000 | F8: 47000
A9: PK-1008 | B9: Electronics & Appliances | C9: Oppo Reno10 | D9: 96 | E9: 82000 | F9: 99000
A10: PK-1009 | B10: Electronics & Appliances | C10: Realme 11 Pro | D10: 34 | E10: 52000 | F10: 65000
A11: PK-1010 | B11: Electronics & Appliances | C11: Xiaomi Redmi 12 | D11: 20 | E11: 34000 | F11: 42000
A12: PK-1011 | B12: Electronics & Appliances | C12: Dell Inspiron 15 | D12: 118 | E12: 115000 | F12: 139000
A13: PK-1012 | B13: Electronics & Appliances | C13: HP Pavilion 14 | D13: 1 | E13: 108000 | F13: 130000
A14: PK-1013 | B14: Electronics & Appliances | C14: Lenovo IdeaPad 3 | D14: 133 | E14: 95000 | F14: 115000
... A215: PK-1214 | B215: Automobiles & Accessories | C215: Dashcam 1080p | D215: 29 | E215: 5500 | F215: 8000

Sheet Inventory
A1: CURRENT INVENTORY STOCK — AL-NOOR TRADING COMPANY
A2: Product ID | B2: Product Name | C2: Category | D2: Sub-Category | E2: SKU | F2: Unit | G2: Qty in Hand | H2: Reorder Level | I2: Reorder Qty | J2: Stock Value (PKR) | K2: Stock Status
A3: PK-1001 | B3: Samsung Galaxy A54 | C3: Electronics & Appliances | D3: Mobile Phones | E3: SMA54 | F3: Unit | G3: 138 | H3: 1 | I3: 10 | J3: =G3*75000 -> 10350000 | K3: In Stock
A4: PK-1002 | B4: Samsung Galaxy A34 | C4: Electronics & Appliances | D4: Mobile Phones | E4: SMA34 | F4: Unit | G4: 74 | H4: 2 | I4: 10 | J4: =G4*55000 -> 4070000 | K4: In Stock
A5: PK-1003 | B5: iPhone 14 | C5: Electronics & Appliances | D5: Mobile Phones | E5: IPH14 | F5: Unit | G5: 7 | H5: 1 | I5: 5 | J5: =G5*240000 -> 1680000 | K5: In Stock
A6: PK-1004 | B6: iPhone 13 | C6: Electronics & Appliances | D6: Mobile Phones | E6: IPH13 | F6: Unit | G6: 53 | H6: 1 | I6: 5 | J6: =G6*185000 -> 9805000 | K6: In Stock
A7: PK-1005 | B7: Vivo Y36 | C7: Electronics & Appliances | D7: Mobile Phones | E7: VIVY36 | F7: Unit | G7: 65 | H7: 3 | I7: 15 | J7: =G7*42000 -> 2730000 | K7: In Stock
A8: PK-1006 | B8: Vivo V27 | C8: Electronics & Appliances | D8: Mobile Phones | E8: VIVV27 | F8: Unit | G8: 12 | H8: 2 | I8: 10 | J8: =G8*65000 -> 780000 | K8: In Stock
A9: PK-1007 | B9: Oppo A78 | C9: Electronics & Appliances | D9: Mobile Phones | E9: OPPA78 | F9: Unit | G9: 101 | H9: 3 | I9: 15 | J9: =G9*38000 -> 3838000 | K9: In Stock
A10: PK-1008 | B10: Oppo Reno10 | C10: Electronics & Appliances | D10: Mobile Phones | E10: OPPR10 | F10: Unit | G10: 96 | H10: 1 | I10: 8 | J10: =G10*82000 -> 7872000 | K10: In Stock
A11: PK-1009 | B11: Realme 11 Pro | C11: Electronics & Appliances | D11: Mobile Phones | E11: RLM11P | F11: Unit | G11: 34 | H11: 3 | I11: 15 | J11: =G11*52000 -> 1768000 | K11: In Stock
A12: PK-1010 | B12: Xiaomi Redmi 12 | C12: Electronics & Appliances | D12: Mobile Phones | E12: XMR12 | F12: Unit | G12: 20 | H12: 4 | I12: 20 | J12: =G12*34000 -> 680000 | K12: In Stock
A13: PK-1011 | B13: Dell Inspiron 15 | C13: Electronics & Appliances | D13: Laptops & Computers | E13: DELI15 | F13: Unit | G13: 118 | H13: 1 | I13: 5 | J13: =G13*115000 -> 13570000 | K13: In Stock
A14: PK-1012 | B14: HP Pavilion 14 | C14: Electronics & Appliances | D14: Laptops & Computers | E14: HPP14 | F14: Unit | G14: 1 | H14: 1 | I14: 5 | J14: =G14*108000 -> 108000 | K14: In Stock
A15: PK-1013 | B15: Lenovo IdeaPad 3 | C15: Electronics & Appliances | D15: Laptops & Computers | E15: LENIP3 | F15: Unit | G15: 133 | H15: 1 | I15: 5 | J15: =G15*95000 -> 12635000 | K15: In Stock
A16: PK-1014 | B16: Asus VivoBook 15 | C16: Electronics & Appliances | D16: Laptops & Computers | E16: ASVB15 | F16: Unit | G16: 62 | H16: 1 | I16: 5 | J16: =G16*105000 -> 6510000 | K16: In Stock
A17: PK-1015 | B17: Dell Latitude 5520 | C17: Electronics & Appliances | D17: Laptops & Computers | E17: DELL5520 | F17: Unit | G17: 6 | H17: 1 | I17: 3 | J17: =G17*175000 -> 1050000 | K17: In Stock
A18: PK-1016 | B18: HP ProBook 450 | C18: Electronics & Appliances | D18: Laptops & Computers | E18: HPPB450 | F18: Unit | G18: 18 | H18: 1 | I18: 3 | J18: =G18*155000 -> 2790000 | K18: In Stock
A19: PK-1017 | B19: Apple MacBook Air M2 | C19: Electronics & Appliances | D19: Laptops & Computers | E19: MBAIM2 | F19: Unit | G19: 40 | H19: 1 | I19: 3 | J19: =G19*290000 -> 11600000 | K19: In Stock
A20: PK-1018 | B20: Acer Aspire 7 | C20: Electronics & Appliances | D20: Laptops & Computers | E20: ACRA7 | F20: Unit | G20: 135 | H20: 2 | I20: 8 | J20: =G20*120000 -> 16200000 | K20: In Stock
A21: PK-1019 | B21: Samsung 43" 4K Smart TV | C21: Electronics & Appliances | D21: Televisions | E21: SMTV43 | F21: Unit | G21: 102 | H21: 1 | I21: 5 | J21: =G21*78000 -> 7956000 | K21: In Stock
A22: PK-1020 | B22: Samsung 55" QLED | C22: Electronics & Appliances | D22: Televisions | E22: SMTV55 | F22: Unit | G22: 89 | H22: 1 | I22: 3 | J22: =G22*150000 -> 13350000 | K22: In Stock
A23: PK-1021 | B23: TCL 40" Smart TV | C23: Electronics & Appliances | D23: Televisions | E23: TCL40 | F23: Unit | G23: 137 | H23: 2 | I23: 8 | J23: =G23*42000 -> 5754000 | K23: In Stock
A24: PK-1022 | B24: TCL 50" 4K TV | C24: Electronics & Appliances | D24: Televisions | E24: TCL50 | F24: Unit | G24: 17 | H24: 1 | I24: 5 | J24: =G24*68000 -> 1156000 | K24: In Stock
A25: PK-1023 | B25: Haier 32" LED | C25: Electronics & Appliances | D25: Televisions | E25: HAI32 | F25: Unit | G25: 102 | H25: 3 | I25: 10 | J25: =G25*28000 -> 2856000 | K25: In Stock
A26: PK-1024 | B26: Haier 43" Smart TV | C26: Electronics & Appliances | D26: Televisions | E26: HAI43 | F26: Unit | G26: 6 | H26: 2 | I26: 8 | J26: =G26*55000 -> 330000 | K26: In Stock
A27: PK-1025 | B27: LG 55" OLED | C27: Electronics & Appliances | D27: Televisions | E27: LGOLED55 | F27: Unit | G27: 63 | H27: 1 | I27: 3 | J27: =G27*195000 -> 12285000 | K27: In Stock
A28: PK-1026 | B28: Sony Bravia 50" | C28: Electronics & Appliances | D28: Televisions | E28: SONY50 | F28: Unit | G28: 144 | H28: 1 | I28: 3 | J28: =G28*125000 -> 18000000 | K28: In Stock
A29: PK-1027 | B29: Dawlance Inverter AC 1.5T | C29: Electronics & Appliances | D29: Home Appliances | E29: DWAC15 | F29: Unit | G29: 71 | H29: 2 | I29: 5 | J29: =G29*95000 -> 6745000 | K29: In Stock
A30: PK-1028 | B30: Haier Inverter AC 1T | C30: Electronics & Appliances | D30: Home Appliances | E30: HAAC1 | F30: Unit | G30: 109 | H30: 2 | I30: 5 | J30: =G30*75000 -> 8175000 | K30: In Stock
A31: PK-1029 | B31: Orient AC 1.5T | C31: Electronics & Appliances | D31: Home Appliances | E31: ORAC15 | F31: Unit | G31: 144 | H31: 2 | I31: 5 | J31: =G31*80000 -> 11520000 | K31: In Stock
A32: PK-1030 | B32: Dawlance Refrigerator 12CF | C32: Electronics & Appliances | D32: Home Appliances | E32: DWREF12 | F32: Unit | G32: 24 | H32: 1 | I32: 4 | J32: =G32*65000 -> 1560000 | K32: In Stock
A33: PK-1031 | B33: Haier Fridge 14CF | C33: Electronics & Appliances | D33: Home Appliances | E33: HAFR14 | F33: Unit | G33: 71 | H33: 1 | I33: 4 | J33: =G33*72000 -> 5112000 | K33: In Stock
A34: PK-1032 | B34: PEL Refrigerator 16CF | C34: Electronics & Appliances | D34: Home Appliances | E34: PELRF16 | F34: Unit | G34: 143 | H34: 1 | I34: 4 | J34: =G34*82000 -> 11726000 | K34: In Stock
A35: PK-1033 | B35: Dawlance Washing Machine | C35: Electronics & Appliances | D35: Home Appliances | E35: DWWM | F35: Unit | G35: 28 | H35: 2 | I35: 5 | J35: =G35*45000 -> 1260000 | K35: In Stock
A36: PK-1034 | B36: Haier Front Load 8kg | C36: Electronics & Appliances | D36: Home Appliances | E36: HAFL8 | F36: Unit | G36: 126 | H36: 1 | I36: 4 | J36: =G36*75000 -> 9450000 | K36: In Stock
A37: PK-1035 | B37: National Microwave 30L | C37: Electronics & Appliances | D37: Home Appliances | E37: NATMW | F37: Unit | G37: 79 | H37: 3 | I37: 8 | J37: =G37*22000 -> 1738000 | K37: In Stock
A38: PK-1036 | B38: Kenwood Blender | C38: Electronics & Appliances | D38: Home Appliances | E38: KENBL | F38: Unit | G38: 33 | H38: 5 | I38: 15 | J38: =G38*3500 -> 115500 | K38: In Stock
A39: PK-1037 | B39: Basmati Rice 25kg | C39: Grocery & Food Items | D39: Staple Foods | E39: BSRC25 | F39: Unit | G39: 79 | H39: 10 | I39: 50 | J39: =G39*3800 -> 300200 | K39: In Stock
A40: PK-1038 | B40: Basmati Rice 5kg | C40: Grocery & Food Items | D40: Staple Foods | E40: BSRC5 | F40: Unit | G40: 79 | H40: 20 | I40: 100 | J40: =G40*800 -> 63200 | K40: In Stock
A41: PK-1039 | B41: Wheat Flour Atta 10kg | C41: Grocery & Food Items | D41: Staple Foods | E41: ATTA10 | F41: Unit | G41: 64 | H41: 15 | I41: 75 | J41: =G41*1100 -> 70400 | K41: In Stock
A42: PK-1040 | B42: Wheat Flour Atta 5kg | C42: Grocery & Food Items | D42: Staple Foods | E42: ATTA5 | F42: Unit | G42: 129 | H42: 25 | I42: 100 | J42: =G42*580 -> 74820 | K42: In Stock
A43: PK-1041 | B43: Sugar 5kg | C43: Grocery & Food Items | D43: Staple Foods | E43: SUGR5 | F43: Unit | G43: 20 | H43: 20 | I43: 100 | J43: =G43*600 -> 12000 | K43: In Stock
A44: PK-1042 | B44: Sugar 1kg | C44: Grocery & Food Items | D44: Staple Foods | E44: SUGR1 | F44: Unit | G44: 35 | H44: 30 | I44: 150 | J44: =G44*125 -> 4375 | K44: In Stock
A45: PK-1043 | B45: Dalda Cooking Oil 5L | C45: Grocery & Food Items | D45: Staple Foods | E45: DLDO5 | F45: Unit | G45: 62 | H45: 15 | I45: 60 | J45: =G45*2000 -> 124000 | K45: In Stock
A46: PK-1044 | B46: Dalda Cooking Oil 1L | C46: Grocery & Food Items | D46: Staple Foods | E46: DLDO1 | F46: Unit | G46: 80 | H46: 30 | I46: 120 | J46: =G46*430 -> 34400 | K46: In Stock
A47: PK-1045 | B47: Sufi Cooking Oil 5L | C47: Grocery & Food Items | D47: Staple Foods | E47: SUFO5 | F47: Unit | G47: 30 | H47: 15 | I47: 60 | J47: =G47*1900 -> 57000 | K47: In Stock
A48: PK-1046 | B48: Canola Oil 3L | C48: Grocery & Food Items | D48: Staple Foods | E48: CNLO3 | F48: Unit | G48: 7 | H48: 20 | I48: 80 | J48: =G48*1100 -> 7700 | K48: Low Stock
A49: PK-1047 | B49: National Biryani Masala 50g | C49: Grocery & Food Items | D49: Spices & Condiments | E49: NBRM50 | F49: Unit | G49: 104 | H49: 20 | I49: 80 | J49: =G49*65 -> 6760 | K49: In Stock
A50: PK-1048 | B50: Shan Biryani Mix 60g | C50: Grocery & Food Items | D50: Spices & Condiments | E50: SHBM60 | F50: Unit | G50: 129 | H50: 20 | I50: 80 | J50: =G50*70 -> 9030 | K50: In Stock
A51: PK-1049 | B51: Shan Karahi Masala 100g | C51: Grocery & Food Items | D51: Spices & Condiments | E51: SHKR100 | F51: Unit | G51: 77 | H51: 20 | I51: 80 | J51: =G51*95 -> 7315 | K51: In Stock
A52: PK-1050 | B52: Mehran Nihari Masala | C52: Grocery & Food Items | D52: Spices & Condiments | E52: MEHNM | F52: Unit | G52: 45 | H52: 20 | I52: 80 | J52: =G52*75 -> 3375 | K52: In Stock
A53: PK-1051 | B53: Turmeric Powder 200g | C53: Grocery & Food Items | D53: Spices & Condiments | E53: TURMRIC | F53: Unit | G53: 134 | H53: 25 | I53: 100 | J53: =G53*55 -> 7370 | K53: In Stock
A54: PK-1052 | B54: Red Chilli Powder 200g | C54: Grocery & Food Items | D54: Spices & Condiments | E54: RCHILLI | F54: Unit | G54: 47 | H54: 25 | I54: 100 | J54: =G54*65 -> 3055 | K54: In Stock
A55: PK-1053 | B55: Garam Masala 100g | C55: Grocery & Food Items | D55: Spices & Condiments | E55: GRAMM | F55: Unit | G55: 120 | H55: 25 | I55: 100 | J55: =G55*75 -> 9000 | K55: In Stock
A56: PK-1054 | B56: Cumin Seeds 100g | C56: Grocery & Food Items | D56: Spices & Condiments | E56: CUMN100 | F56: Unit | G56: 84 | H56: 30 | I56: 100 | J56: =G56*50 -> 4200 | K56: In Stock
A57: PK-1055 | B57: Black Pepper 50g | C57: Grocery & Food Items | D57: Spices & Condiments | E57: BLKP50 | F57: Unit | G57: 131 | H57: 30 | I57: 100 | J57: =G57*70 -> 9170 | K57: In Stock
A58: PK-1056 | B58: Coriander Powder 200g | C58: Grocery & Food Items | D58: Spices & Condiments | E58: CORP200 | F58: Unit | G58: 115 | H58: 25 | I58: 100 | J58: =G58*58 -> 6670 | K58: In Stock
A59: PK-1057 | B59: Nescafé Classic 200g | C59: Grocery & Food Items | D59: Beverages | E59: NESCF200 | F59: Unit | G59: 85 | H59: 10 | I59: 40 | J59: =G59*1350 -> 114750 | K59: In Stock
A60: PK-1058 | B60: Tapal Danedar 500g | C60: Grocery & Food Items | D60: Beverages | E60: TAPDN500 | F60: Unit | G60: 133 | H60: 15 | I60: 60 | J60: =G60*580 -> 77140 | K60: In Stock
A61: PK-1059 | B61: Lipton Yellow Label 200g | C61: Grocery & Food Items | D61: Beverages | E61: LIPYL200 | F61: Unit | G61: 86 | H61: 15 | I61: 60 | J61: =G61*650 -> 55900 | K61: In Stock
A62: PK-1060 | B62: Tang Mango 500g | C62: Grocery & Food Items | D62: Beverages | E62: TNGMNG | F62: Unit | G62: 17 | H62: 15 | I62: 60 | J62: =G62*350 -> 5950 | K62: In Stock
A63: PK-1061 | B63: Rooh Afza 800ml | C63: Grocery & Food Items | D63: Beverages | E63: RFAHZA | F63: Unit | G63: 5 | H63: 10 | I63: 40 | J63: =G63*480 -> 2400 | K63: Low Stock
A64: PK-1062 | B64: Pepsi 1.5L | C64: Grocery & Food Items | D64: Beverages | E64: PEPSI15 | F64: Unit | G64: 26 | H64: 30 | I64: 120 | J64: =G64*120 -> 3120 | K64: Low Stock
A65: PK-1063 | B65: Coca-Cola 1.5L | C65: Grocery & Food Items | D65: Beverages | E65: COKE15 | F65: Unit | G65: 121 | H65: 30 | I65: 120 | J65: =G65*120 -> 14520 | K65: In Stock
A66: PK-1064 | B66: Minute Maid 1L | C66: Grocery & Food Items | D66: Beverages | E66: MNJCE1L | F66: Unit | G66: 124 | H66: 20 | I66: 80 | J66: =G66*150 -> 18600 | K66: In Stock
A67: PK-1065 | B67: Olper Milk 1L | C67: Grocery & Food Items | D67: Beverages | E67: OLPRMK | F67: Unit | G67: 66 | H67: 40 | I67: 200 | J67: =G67*180 -> 11880 | K67: In Stock
A68: PK-1066 | B68: Nurpur Butter 200g | C68: Grocery & Food Items | D68: Beverages | E68: NURBT200 | F68: Unit | G68: 122 | H68: 20 | I68: 80 | J68: =G68*250 -> 30500 | K68: In Stock
A69: PK-1067 | B69: Olpers Full Cream Milk 1L | C69: Grocery & Food Items | D69: Dairy & Frozen | E69: OLFCM | F69: Unit | G69: 64 | H69: 40 | I69: 200 | J69: =G69*185 -> 11840 | K69: In Stock
A70: PK-1068 | B70: Nestle Everyday Milk Powder 1kg | C70: Grocery & Food Items | D70: Dairy & Frozen | E70: NESEDAY | F70: Unit | G70: 148 | H70: 10 | I70: 40 | J70: =G70*1200 -> 177600 | K70: In Stock
A71: PK-1069 | B71: Haleeb Milk 1L | C71: Grocery & Food Items | D71: Dairy & Frozen | E71: HLBMK | F71: Unit | G71: 65 | H71: 40 | I71: 200 | J71: =G71*180 -> 11700 | K71: In Stock
A72: PK-1070 | B72: Sapphire Yogurt 1kg | C72: Grocery & Food Items | D72: Dairy & Frozen | E72: SAPPYG | F72: Unit | G72: 43 | H72: 20 | I72: 80 | J72: =G72*280 -> 12040 | K72: In Stock
A73: PK-1071 | B73: Yummy Cheddar Slice 200g | C73: Grocery & Food Items | D73: Dairy & Frozen | E73: YUMCHD | F73: Unit | G73: 47 | H73: 15 | I73: 60 | J73: =G73*350 -> 16450 | K73: In Stock
A74: PK-1072 | B74: K&N's Chicken Nuggets 500g | C74: Grocery & Food Items | D74: Dairy & Frozen | E74: KNCNG500 | F74: Unit | G74: 47 | H74: 15 | I74: 60 | J74: =G74*680 -> 31960 | K74: In Stock
A75: PK-1073 | B75: K&N's Chicken Strips 400g | C75: Grocery & Food Items | D75: Dairy & Frozen | E75: KNCST400 | F75: Unit | G75: 131 | H75: 15 | I75: 60 | J75: =G75*750 -> 98250 | K75: In Stock
A76: PK-1074 | B76: Dawn Croissant 6pcs | C76: Grocery & Food Items | D76: Dairy & Frozen | E76: DWNCRS | F76: Unit | G76: 72 | H76: 20 | I76: 80 | J76: =G76*280 -> 20160 | K76: In Stock
A77: PK-1075 | B77: Gul Ahmed Lawn Suit 3pc | C77: Clothing & Textiles | D77: Men's Wear | E77: GALWN3 | F77: Unit | G77: 107 | H77: 10 | I77: 30 | J77: =G77*1200 -> 128400 | K77: In Stock
A78: PK-1076 | B78: Almirah Men Kurta | C78: Clothing & Textiles | D78: Men's Wear | E78: ALMKRT | F78: Unit | G78: 57 | H78: 10 | I78: 30 | J78: =G78*1500 -> 85500 | K78: In Stock
A79: PK-1077 | B79: Khaadi Men Shalwar Kameez | C79: Clothing & Textiles | D79: Men's Wear | E79: KHDSK | F79: Unit | G79: 54 | H79: 10 | I79: 30 | J79: =G79*2500 -> 135000 | K79: In Stock
A80: PK-1078 | B80: J. Men Shirt | C80: Clothing & Textiles | D80: Men's Wear | E80: JMSHRT | F80: Unit | G80: 122 | H80: 10 | I80: 30 | J80: =G80*1800 -> 219600 | K80: In Stock
A81: PK-1079 | B81: Bonanza Men Sweater | C81: Clothing & Textiles | D81: Men's Wear | E81: BNSSWT | F81: Unit | G81: 94 | H81: 5 | I81: 20 | J81: =G81*2200 -> 206800 | K81: In Stock
A82: PK-1080 | B82: Men Denim Jeans 32 | C82: Clothing & Textiles | D82: Men's Wear | E82: MDNJNS32 | F82: Unit | G82: 110 | H82: 10 | I82: 30 | J82: =G82*1400 -> 154000 | K82: In Stock
A83: PK-1081 | B83: Men Denim Jeans 34 | C83: Clothing & Textiles | D83: Men's Wear | E83: MDNJNS34 | F83: Unit | G83: 76 | H83: 10 | I83: 30 | J83: =G83*1400 -> 106400 | K83: In Stock
A84: PK-1082 | B84: Men Formal Trouser | C84: Clothing & Textiles | D84: Men's Wear | E84: MFRTRS | F84: Unit | G84: 130 | H84: 10 | I84: 30 | J84: =G84*1600 -> 208000 | K84: In Stock
A85: PK-1083 | B85: Men Polo T-Shirt | C85: Clothing & Textiles | D85: Men's Wear | E85: MPTSHRT | F85: Unit | G85: 97 | H85: 15 | I85: 40 | J85: =G85*650 -> 63050 | K85: In Stock
A86: PK-1084 | B86: Men Sports Shorts | C86: Clothing & Textiles | D86: Men's Wear | E86: MSPSHRT | F86: Unit | G86: 97 | H86: 15 | I86: 40 | J86: =G86*700 -> 67900 | K86: In Stock
A87: PK-1085 | B87: Gul Ahmed Summer Collection 3pc | C87: Clothing & Textiles | D87: Women's Wear | E87: GALSC3 | F87: Unit | G87: 77 | H87: 10 | I87: 25 | J87: =G87*1800 -> 138600 | K87: In Stock
A88: PK-1086 | B88: Sana Safinaz Ready-to-Wear | C88: Clothing & Textiles | D88: Women's Wear | E88: SNSFRTW | F88: Unit | G88: 120 | H88: 5 | I88: 15 | J88: =G88*4500 -> 540000 | K88: In Stock
A89: PK-1087 | B89: Khaadi Pret Kurta | C89: Clothing & Textiles | D89: Women's Wear | E89: KHDPRTKRT | F89: Unit | G89: 95 | H89: 8 | I89: 20 | J89: =G89*2200 -> 209000 | K89: In Stock
A90: PK-1088 | B90: Maria B Lawn 3pc | C90: Clothing & Textiles | D90: Women's Wear | E90: MBLWN3 | F90: Unit | G90: 79 | H90: 8 | I90: 20 | J90: =G90*3200 -> 252800 | K90: In Stock
A91: PK-1089 | B91: Nishat Linen Suit | C91: Clothing & Textiles | D91: Women's Wear | E91: NSHLNN | F91: Unit | G91: 132 | H91: 8 | I91: 20 | J91: =G91*2800 -> 369600 | K91: In Stock
A92: PK-1090 | B92: Zellbury Kurta Set | C92: Clothing & Textiles | D92: Women's Wear | E92: ZLBKRT | F92: Unit | G92: 35 | H92: 10 | I92: 25 | J92: =G92*1500 -> 52500 | K92: In Stock
A93: PK-1091 | B93: Women Capri Pants | C93: Clothing & Textiles | D93: Women's Wear | E93: WCPRI | F93: Unit | G93: 40 | H93: 15 | I93: 40 | J93: =G93*800 -> 32000 | K93: In Stock
A94: PK-1092 | B94: Women Cardigan | C94: Clothing & Textiles | D94: Women's Wear | E94: WCRDGN | F94: Unit | G94: 75 | H94: 10 | I94: 25 | J94: =G94*1500 -> 112500 | K94: In Stock
A95: PK-1093 | B95: Women Abaya Plain | C95: Clothing & Textiles | D95: Women's Wear | E95: WABPLN | F95: Unit | G95: 135 | H95: 8 | I95: 20 | J95: =G95*1800 -> 243000 | K95: In Stock
A96: PK-1094 | B96: Women Dupatta Lawn | C96: Clothing & Textiles | D96: Women's Wear | E96: WDPLWN | F96: Unit | G96: 82 | H96: 20 | I96: 60 | J96: =G96*500 -> 41000 | K96: In Stock
A97: PK-1095 | B97: Bata Men Leather Shoes | C97: Clothing & Textiles | D97: Footwear | E97: BATMS | F97: Unit | G97: 5 | H97: 5 | I97: 15 | J97: =G97*3500 -> 17500 | K97: In Stock
A98: PK-1096 | B98: Bata Women Pumps | C98: Clothing & Textiles | D98: Footwear | E98: BATWS | F98: Unit | G98: 48 | H98: 5 | I98: 15 | J98: =G98*2800 -> 134400 | K98: In Stock
A99: PK-1097 | B99: Servis Men Sandals | C99: Clothing & Textiles | D99: Footwear | E99: SRVMS | F99: Unit | G99: 30 | H99: 10 | I99: 20 | J99: =G99*1200 -> 36000 | K99: In Stock
A100: PK-1098 | B100: Servis School Shoes | C100: Clothing & Textiles | D100: Footwear | E100: SRVSS | F100: Unit | G100: 85 | H100: 8 | I100: 20 | J100: =G100*1500 -> 127500 | K100: In Stock
...

Sheet Suppliers
A1: SUPPLIER MASTER — AL-NOOR TRADING COMPANY
A2: Supplier ID | B2: Supplier Name | C2: Category | D2: Contact Person | E2: Phone | F2: Email | G2: City | H2: Credit Terms (Days) | I2: Credit Limit (PKR) | J2: Status
A3: SUP-001 | B3: TechHub Pvt Ltd | C3: Electronics | D3: Ahmed Khan | E3: 0300-1234567 | F3: ahmed@techhub.pk | G3: Lahore | H3: 30 | I3: 500000 | J3: Active
A4: SUP-002 | B4: iWorld Pakistan | C4: Electronics | D4: Sara Ali | E4: 0321-2345678 | F4: sara@iworld.pk | G4: Karachi | H4: 15 | I4: 1000000 | J4: Active
A5: SUP-003 | B5: Vivo Pakistan | C5: Electronics | D5: Bilal Malik | E5: 0333-3456789 | F5: bilal@vivo.pk | G5: Lahore | H5: 30 | I5: 600000 | J5: Active
A6: SUP-004 | B6: Oppo Distributors | C6: Electronics | D6: Zain Raza | E6: 0345-4567890 | F6: zain@oppo.pk | G6: Islamabad | H6: 30 | I6: 500000 | J6: Active
A7: SUP-005 | B7: Realme Pakistan | C7: Electronics | D7: Ayesha Butt | E7: 0301-5678901 | F7: ayesha@realme.pk | G7: Lahore | H7: 30 | I7: 400000 | J7: Active
A8: SUP-006 | B8: Xiaomi Pakistan | C8: Electronics | D8: Kamran Iqbal | E8: 0311-6789012 | F8: kamran@xiaomi.pk | G8: Lahore | H8: 30 | I8: 450000 | J8: Active
A9: SUP-007 | B9: Dell Pakistan | C9: Computers | D9: Sobia Hashmi | E9: 0321-7890123 | F9: sobia@dell.pk | G9: Karachi | H9: 45 | I9: 800000 | J9: Active
A10: SUP-008 | B10: HP Distributors | C10: Computers | D10: Asif Mehmood | E10: 0333-8901234 | F10: asif@hp.pk | G10: Lahore | H10: 45 | I10: 700000 | J10: Active
A11: SUP-009 | B11: Lenovo Pakistan | C11: Computers | D11: Rabia Noor | E11: 0300-9012345 | F11: rabia@lenovo.pk | G11: Islamabad | H11: 45 | I11: 600000 | J11: Active
A12: SUP-010 | B12: Asus Pakistan | C12: Computers | D12: Tariq Javed | E12: 0321-0123456 | F12: tariq@asus.pk | G12: Karachi | H12: 45 | I12: 550000 | J12: Active
A13: SUP-011 | B13: Acer Pakistan | C13: Computers | D13: Hina Shah | E13: 0345-1234567 | F13: hina@acer.pk | G13: Lahore | H13: 45 | I13: 500000 | J13: Active
A14: SUP-012 | B14: TCL Pakistan | C14: Electronics | D14: Usman Ghani | E14: 0301-2345678 | F14: usman@tcl.pk | G14: Lahore | H14: 30 | I14: 400000 | J14: Active
... A62: SUP-060 | B62: Casio Pakistan | C62: Electronics | D62: Tariq Bashir | E62: 0301-0123458 | F62: tariq@casio.pk | G62: Lahore | H62: 30 | I62: 250000 | J62: Active

Sheet Customers
A1: CUSTOMER MASTER — AL-NOOR TRADING COMPANY
A2: Customer ID | B2: Customer Name | C2: Type | D2: Phone | E2: Email | F2: City | G2: Address | H2: Credit Limit (PKR) | I2: Credit Terms (Days) | J2: Total Purchases (PKR) | K2: Status
A3: CUST-001 | B3: Malik General Store | C3: Retail | D3: 0300-1111001 | E3: malik.store@gmail.com | F3: Lahore | G3: Shop 5, Hall Road, Lahore | H3: 50000 | I3: 7 | J3: 250000 | K3: Active
A4: CUST-002 | B4: Ahmed Electronics | C4: Wholesale | D4: 0321-2222002 | E4: ahmed.elec@gmail.com | F4: Lahore | G4: Plot 12, Brandreth Road | H4: 200000 | I4: 30 | J4: 1500000 | K4: Active
A5: CUST-003 | B5: City Supermarket | C5: Retail | D5: 0333-3333003 | E5: city.super@gmail.com | F5: Lahore | G5: Main Boulevard, Gulberg | H5: 100000 | I5: 15 | J5: 800000 | K5: Active
A6: CUST-004 | B6: Punjab Traders | C6: Wholesale | D6: 0345-4444004 | E6: punjab.traders@hotmail.com | F6: Lahore | G6: Anarkali Bazaar, Lahore | H6: 500000 | I6: 30 | J6: 3500000 | K6: Active
A7: CUST-005 | B7: Karachi Distributors | C7: Distributor | D7: 0301-5555005 | E7: khi.dist@gmail.com | F7: Karachi | G7: Saddar, Karachi | H7: 800000 | I7: 45 | J7: 6000000 | K7: Active
A8: CUST-006 | B8: Islamabad Stores | C8: Retail | D8: 0311-6666006 | E8: isb.stores@gmail.com | F8: Islamabad | G8: F-10 Markaz, Islamabad | H8: 75000 | I8: 15 | J8: 450000 | K8: Active
A9: CUST-007 | B9: Al-Fatah Department Store | C9: Corporate | D9: 0333-7777007 | E9: alfatah@gmail.com | F9: Lahore | G9: Mall Road, Lahore | H9: 300000 | I9: 30 | J9: 2500000 | K9: Active
A10: CUST-008 | B10: Imtiaz Super Market | C10: Corporate | D10: 0300-8888008 | E10: imtiaz.super@gmail.com | F10: Karachi | G10: Bahadurabad, Karachi | H10: 400000 | I10: 30 | J10: 3200000 | K10: Active
A11: CUST-009 | B11: Rawalpindi Wholesale | C11: Wholesale | D11: 0321-9999009 | E11: rwp.whole@gmail.com | F11: Rawalpindi | G11: Raja Bazaar, Rawalpindi | H11: 600000 | I11: 45 | J11: 4500000 | K11: Active
A12: CUST-010 | B12: Faisalabad Cloth Merchant | C12: Wholesale | D12: 0345-1010010 | E12: fsd.cloth@gmail.com | F12: Faisalabad | G12: Clock Tower, Faisalabad | H12: 400000 | I12: 30 | J12: 3000000 | K12: Active
A13: CUST-011 | B13: Imran Khan Enterprises | C13: Wholesale | D13: 0302-2719583 | E13: imran.khan@gmail.com | F13: Rawalpindi | G13: Street 6, Rawalpindi | H13: 800000 | I13: 30 | J13: 4674866 | K13: Active
A14: CUST-012 | B14: Sobia Ali General Store | C14: Retail | D14: 0303-4903402 | E14: sobia.ali@gmail.com | F14: Karachi | G14: Street 36, Karachi | H14: 500000 | I14: 7 | J14: 322599 | K14: Active
... A102: CUST-100 | B102: Faisal Qureshi Sons | C102: Corporate | D102: 0308-9284509 | E102: faisal.qureshi@gmail.com | F102: Sialkot | G102: Street 39, Sialkot | H102: 300000 | I102: 45 | J102: 774795 | K102: Active

Sheet Sales Orders
A1: SALES ORDERS — AL-NOOR TRADING COMPANY (Jan–Dec 2024)
A2: SO Number | B2: Date | C2: Customer ID | D2: Customer Name | E2: Product ID | F2: Product Name | G2: Category | H2: Qty Sold | I2: Cost Price (PKR) | J2: Sale Price (PKR) | K2: Total Revenue (PKR) | L2: Total Cost (PKR) | M2: Gross Profit (PKR)
A3: SO-2024001 | B3: 2024-12-17 | C3: CUST-099 | D3: Kashif Malik General Store | E3: BRFL500 | F3: Brake Fluid DOT4 500ml | G3: Automobiles & Accessories | H3: 10 | I3: 320 | J3: 480 | K3: =H3*J3 -> 4800 | L3: =H3*I3 -> 3200 | M3: =K3-L3 -> 1600
A4: SO-2024002 | B4: 2024-05-13 | C4: CUST-082 | D4: Rabia Iqbal Co. | E4: SPNBA4 | F4: Spiral Notebook A4 | G4: Stationery & Office Supplies | H4: 7 | I4: 180 | J4: 270 | K4: =H4*J4 -> 1890 | L4: =H4*I4 -> 1260 | M4: =K4-L4 -> 630
A5: SO-2024003 | B5: 2024-06-16 | C5: CUST-022 | D5: Nadia Iqbal Traders | E5: DSPRN10 | F5: Disprin 10tabs | G5: Pharmaceuticals & Health | H5: 2 | I5: 45 | J5: 70 | K5: =H5*J5 -> 140 | L5: =H5*I5 -> 90 | M5: =K5-L5 -> 50
A6: SO-2024004 | B6: 2024-07-29 | C6: CUST-010 | D6: Faisalabad Cloth Merchant | E6: CTNFBR | F6: Cotton Fabric per meter | G6: Clothing & Textiles | H6: 7 | I6: 200 | J6: 310 | K6: =H6*J6 -> 2170 | L6: =H6*I6 -> 1400 | M6: =K6-L6 -> 770
A7: SO-2024005 | B7: 2024-03-05 | C7: CUST-061 | D7: Sana Iqbal Distributors | E7: MFRTRS | F7: Men Formal Trouser | G7: Clothing & Textiles | H7: 38 | I7: 1600 | J7: 2400 | K7: =H7*J7 -> 91200 | L7: =H7*I7 -> 60800 | M7: =K7-L7 -> 30400
A8: SO-2024006 | B8: 2024-08-18 | C8: CUST-027 | D8: Faisal Raza General Store | E8: SLKFBR | F8: Silk Fabric per meter | G8: Clothing & Textiles | H8: 13 | I8: 700 | J8: 1050 | K8: =H8*J8 -> 13650 | L8: =H8*I8 -> 9100 | M8: =K8-L8 -> 4550
A9: SO-2024007 | B9: 2024-06-11 | C9: CUST-088 | D9: Faisal Shah Distributors | E9: GLCMTR | F9: Glucometer | G9: Pharmaceuticals & Health | H9: 22 | I9: 3500 | J9: 5200 | K9: =H9*J9 -> 114400 | L9: =H9*I9 -> 77000 | M9: =K9-L9 -> 37400
A10: SO-2024008 | B10: 2024-06-17 | C10: CUST-012 | D10: Sobia Ali General Store | E10: MNTIE | F10: Men Necktie | G10: Clothing & Textiles | H10: 41 | I10: 550 | J10: 900 | K10: =H10*J10 -> 36900 | L10: =H10*I10 -> 22550 | M10: =K10-L10 -> 14350
A11: SO-2024009 | B11: 2024-09-22 | C11: CUST-063 | D11: Mehwish Malik Co. | E11: AGSBT40 | F11: AGS Battery 40Ah | G11: Automobiles & Accessories | H11: 26 | I11: 10500 | J11: 14000 | K11: =H11*J11 -> 364000 | L11: =H11*I11 -> 273000 | M11: =K11-L11 -> 91000
A12: SO-2024010 | B12: 2024-02-11 | C12: CUST-074 | D12: Hina Hussain Distributors | E12: GRAMM | F12: Garam Masala 100g | G12: Grocery & Food Items | H12: 16 | I12: 75 | J12: 105 | K12: =H12*J12 -> 1680 | L12: =H12*I12 -> 1200 | M12: =K12-L12 -> 480
A13: SO-2024011 | B13: 2024-01-18 | C13: CUST-013 | D13: Bilal Qureshi Pvt Ltd | E13: RCHILLI | F13: Red Chilli Powder 200g | G13: Grocery & Food Items | H13: 6 | I13: 65 | J13: 90 | K13: =H13*J13 -> 540 | L13: =H13*I13 -> 390 | M13: =K13-L13 -> 150
A14: SO-2024012 | B14: 2024-04-07 | C14: CUST-089 | D14: Tariq Raza Distributors | E14: OLPRMK | F14: Olper Milk 1L | G14: Grocery & Food Items | H14: 49 | I14: 180 | J14: 240 | K14: =H14*J14 -> 11760 | L14: =H14*I14 -> 8820 | M14: =K14-L14 -> 2940
... A302: SO-2024300 | B302: 2024-07-18 | C302: CUST-090 | D302: Bilal Shah Distributors | E302: OPPR10 | F302: Oppo Reno10 | G302: Electronics & Appliances | H302: 4 | I302: 82000 | J302: 99000 | K302: =H302*J302 -> 396000 | L302: =H302*I302 -> 328000 | M302: =K302-L302 -> 68000

Sheet Employees
A1: EMPLOYEE MASTER — AL-NOOR TRADING COMPANY
A2: Employee ID | B2: Name | C2: Department | D2: Designation | E2: Date of Joining | F2: Salary (PKR) | G2: Phone | H2: Email | I2: City | J2: CNIC | K2: Bank Account | L2: Status
A3: EMP-001 | B3: Muhammad Aslam | C3: Management | D3: CEO | E3: 2015-01-01 | F3: 250000 | G3: 0300-1001001 | H3: m.aslam@alnoor.pk | I3: Lahore | J3: 35201-1234567-1 | K3: 0010001234567 | L3: Active
A4: EMP-002 | B4: Tariq Nawaz | C4: Management | D4: CFO | E4: 2016-03-15 | F4: 180000 | G4: 0321-2002002 | H4: t.nawaz@alnoor.pk | I4: Lahore | J4: 35202-2345678-2 | K4: 0010002345678 | L4: Active
A5: EMP-003 | B5: Shahida Perveen | C5: HR | D5: HR Manager | E5: 2017-06-01 | F5: 90000 | G5: 0333-3003003 | H5: s.perveen@alnoor.pk | I5: Lahore | J5: 35203-3456789-3 | K5: 0010003456789 | L5: Active
A6: EMP-004 | B6: Bilal Ahmed | C6: Sales | D6: Sales Manager | E6: 2018-02-10 | F6: 80000 | G6: 0345-4004004 | H6: b.ahmed@alnoor.pk | I6: Lahore | J6: 35204-4567890-4 | K6: 0010004567890 | L6: Active
A7: EMP-005 | B7: Farrukh Saleem | C7: Purchase | D7: Purchase Manager | E7: 2018-05-20 | F7: 75000 | G7: 0301-5005005 | H7: f.saleem@alnoor.pk | I7: Lahore | J7: 35205-5678901-5 | K7: 0010005678901 | L7: Active
A8: EMP-006 | B8: Hina Qureshi | C8: Finance | D8: Senior Accountant | E8: 2019-01-15 | F8: 65000 | G8: 0311-6006006 | H8: h.qureshi@alnoor.pk | I8: Lahore | J8: 35206-6789012-6 | K8: 0010006789012 | L8: Active
A9: EMP-007 | B9: Kamran Iqbal | C9: IT | D9: IT Manager | E9: 2019-07-01 | F9: 70000 | G9: 0333-7007007 | H9: k.iqbal@alnoor.pk | I9: Lahore | J9: 35207-7890123-7 | K9: 0010007890123 | L9: Active
A10: EMP-008 | B10: Sana Malik | C10: Sales | D10: Sales Executive | E10: 2020-03-01 | F10: 45000 | G10: 0300-8008008 | H10: s.malik@alnoor.pk | I10: Lahore | J10: 35208-8901234-8 | K10: 0010008901234 | L10: Active
A11: EMP-009 | B11: Usman Ghani | C11: Sales | D11: Sales Executive | E11: 2020-06-15 | F11: 42000 | G11: 0321-9009009 | H11: u.ghani@alnoor.pk | I11: Lahore | J11: 35209-9012345-9 | K11: 0010009012345 | L11: Active
A12: EMP-010 | B12: Nadia Waseem | C12: Sales | D12: Sales Executive | E12: 2020-09-01 | F12: 42000 | G12: 0345-1010010 | H12: n.waseem@alnoor.pk | I12: Lahore | J12: 35210-0123456-0 | K12: 0010000123456 | L12: Active
A13: EMP-011 | B13: Asif Raza | C13: Warehouse | D13: Warehouse Manager | E13: 2017-04-01 | F13: 65000 | G13: 0301-1111011 | H13: a.raza@alnoor.pk | I13: Lahore | J13: 35201-1111111-1 | K13: 0010001111111 | L13: Active
A14: EMP-012 | B14: Imran Butt | C14: Warehouse | D14: Store Keeper | E14: 2019-11-01 | F14: 35000 | G14: 0311-1212012 | H14: i.butt@alnoor.pk | I14: Lahore | J14: 35201-2222222-2 | K14: 0010002222222 | L14: Active
... A22: EMP-020 | B22: Aamir Khan | C22: IT | D22: IT Support | E22: 2022-06-01 | F22: 40000 | G22: 0300-2020020 | H22: a.khan@alnoor.pk | I22: Lahore | J22: 35202-0000000-0 | K22: 0010000000000 | L22: Active

Sheet Summary Dashboard
A1: ERP SUMMARY DASHBOARD — AL-NOOR TRADING CO. (FY 2024)
A4: BUSINESS OVERVIEW
A5: Total Products in Catalog | B5: =COUNTA(Products!A3:A1000)-1 -> 213 | D5: Total Suppliers | E5: =COUNTA(Suppliers!A3:A100)-1 -> 59
A6: Total Customers | B6: =COUNTA(Customers!A3:A200)-1 -> 99 | D6: Total Employees | E6: =COUNTA(Employees!A3:A50)-1 -> 19
A8: INVENTORY SUMMARY
A9: Total SKUs In Stock | B9: =COUNTIF(Inventory!K3:K1000,"In Stock") -> 202 | D9: Low Stock Items | E9: =COUNTIF(Inventory!K3:K1000,"Low Stock") -> 12
A10: Out of Stock Items | B10: =COUNTIF(Inventory!K3:K1000,"Out of Stock") -> 0 | D10: Total Stock Value (PKR) | E10: =SUM(Inventory!J3:J1000) -> 245258985
A12: SALES SUMMARY (2024)
A13: Total Sales Orders | B13: =COUNTA('Sales Orders'!A3:A500)-1 -> 299 | D13: Total Revenue (PKR) | E13: =SUM('Sales Orders'!K3:K500) -> 150549505
A14: Total Cost of Goods (PKR) | B14: =SUM('Sales Orders'!L3:L500) -> 122431193 | D14: Total Gross Profit (PKR) | E14: =SUM('Sales Orders'!M3:M500) -> 28118312
A16: PURCHASE SUMMARY (2024)
A17: Total Purchase Orders | B17: =COUNTA('Purchase Orders'!A3:A500)-1 -> 199 | D17: Total Purchases Value (PKR) | E17: =SUM('Purchase Orders'!J3:J500) -> 190014470
A18: Received Orders | B18: =COUNTIF('Purchase Orders'!K3:K500,"Received") -> 43 | D18: Pending Orders | E18: =COUNTIF('Purchase Orders'!K3:K500,"Pending") -> 49
